README.txt
setup.py
googlefinance/__init__.py
googlefinance/client.py
googlefinance.client.egg-info/PKG-INFO
googlefinance.client.egg-info/SOURCES.txt
googlefinance.client.egg-info/dependency_links.txt
googlefinance.client.egg-info/requires.txt
googlefinance.client.egg-info/top_level.txt