Metadata-Version: 1.1
Name: googlefinance.client
Version: 0.1.0
Summary: googlefinance.client is a python client library for google finance.
Home-page: https://github.com/pdevty/googlefinance-client-python
Author: pdevty
Author-email: p.dev.ty@gmail.com
License: MIT
Keywords: googlefinance
Platform: UNKNOWN
Classifier: Programming Language :: Python :: 3.6
Classifier: Intended Audience :: Financial and Insurance Industry
Classifier: License :: OSI Approved :: MIT License
